pylibutils/__init__.py
pylibutils/constants.py
pylibutils/patterns.py
pylibutils/tests/test_utils.py
pylibutils/utils.py
pylibutils-0.1.1.dist-info/LICENSE
pylibutils-0.1.1.dist-info/METADATA
pylibutils-0.1.1.dist-info/WHEEL
pylibutils-0.1.1.dist-info/RECORD
