Metadata-Version: 2.3
Name: pylibutils
Version: 0.1.1
Summary: Python library for common utilities.
License: Apache-2.0
Author: Mouad Kommir
Author-email: mouadkommir@gmail.com
Requires-Python: >=3.12
Classifier: Development Status :: 4 - Beta
Classifier: License :: OSI Approved :: Apache Software License
Classifier: Operating System :: MacOS :: MacOS X
Classifier: Operating System :: POSIX :: Linux
Classifier: Programming Language :: Python :: 3
Classifier: Programming Language :: Python :: 3.12
Classifier: Programming Language :: Python :: 3.13
Classifier: Topic :: Software Development :: Libraries :: Python Modules
